granite_io/__init__.py
granite_io/_version.py
granite_io/factory.py
granite_io/optional.py
granite_io/types.py
granite_io/backend/__init__.py
granite_io/backend/base.py
granite_io/backend/litellm.py
granite_io/backend/openai.py
granite_io/backend/registry.py
granite_io/backend/transformers.py
granite_io/backend/vllm_server.py
granite_io/io/__init__.py
granite_io/io/base.py
granite_io/io/consts.py
granite_io/io/registry.py
granite_io/io/answerability/__init__.py
granite_io/io/answerability/answerability.py
granite_io/io/certainty/__init__.py
granite_io/io/certainty/certainty.py
granite_io/io/citations/__init__.py
granite_io/io/citations/citations.py
granite_io/io/context_relevancy/__init__.py
granite_io/io/context_relevancy/context_relevancy.py
granite_io/io/granite_3_2/__init__.py
granite_io/io/granite_3_2/granite_3_2.py
granite_io/io/granite_3_2/input_processors/__init__.py
granite_io/io/granite_3_2/input_processors/granite_3_2_input_processor.py
granite_io/io/granite_3_2/output_processors/__init__.py
granite_io/io/granite_3_2/output_processors/granite_3_2_output_parser.py
granite_io/io/granite_3_2/output_processors/granite_3_2_output_processor.py
granite_io/io/granite_3_3/__init__.py
granite_io/io/granite_3_3/granite_3_3.py
granite_io/io/granite_3_3/input_processors/__init__.py
granite_io/io/granite_3_3/input_processors/granite_3_3_input_processor.py
granite_io/io/granite_3_3/output_processors/__init__.py
granite_io/io/granite_3_3/output_processors/granite_3_3_output_parser.py
granite_io/io/granite_3_3/output_processors/granite_3_3_output_processor.py
granite_io/io/hallucinations/__init__.py
granite_io/io/hallucinations/hallucinations.py
granite_io/io/hyde_rewrite/__init__.py
granite_io/io/hyde_rewrite/hyde_rewrite.py
granite_io/io/llmrerank/README.md
granite_io/io/llmrerank/__init__.py
granite_io/io/llmrerank/llmrerank.py
granite_io/io/llmrerank/images/Picture1.png
granite_io/io/process_reward_model/__init__.py
granite_io/io/process_reward_model/best_of_n.py
granite_io-0.5.2.dist-info/licenses/LICENSE
granite_io-0.5.2.dist-info/METADATA
granite_io-0.5.2.dist-info/WHEEL
granite_io-0.5.2.dist-info/top_level.txt
granite_io-0.5.2.dist-info/RECORD
