Metadata-Version: 2.4
Name: granite-io
Version: 0.5.2
Summary: Input and output processing for IBM Granite models
Author-email: Fred Reiss <frreiss@us.ibm.com>, Gabe Goodhart <ghart@us.ibm.com>, Mark Sturdevant <mark.sturdevant@ibm.com>, Martin Hickey <martin.hickey@ie.ibm.com>
Project-URL: homepage, https://github.com/ibm-granite/granite-io
Project-URL: source, https://github.com/ibm-granite/granite-io
Project-URL: issues, https://github.com/ibm-granite/granite-io/issues
Classifier: Development Status :: 3 - Alpha
Classifier: License :: OSI Approved :: Apache Software License
Classifier: Operating System :: POSIX :: Linux
Classifier: Operating System :: MacOS :: MacOS X
Classifier: Topic :: Scientific/Engineering :: Artificial Intelligence
Classifier: Programming Language :: Python :: 3
Classifier: Programming Language :: Python :: 3.10
Classifier: Programming Language :: Python :: 3.11
Classifier: Programming Language :: Python :: 3.12
Classifier: Programming Language :: Python :: Implementation :: CPython
Requires-Python: >=3.10
License-File: LICENSE
Requires-Dist: alchemy-config
Requires-Dist: jsonschema
Requires-Dist: pydantic>=2.0.0
Requires-Dist: rouge_score
Requires-Dist: aiohttp
Provides-Extra: transformers
Requires-Dist: transformers[torch]; extra == "transformers"
Provides-Extra: nltk
Requires-Dist: nltk~=3.9.1; extra == "nltk"
Provides-Extra: openai
Requires-Dist: openai>1.100; extra == "openai"
Provides-Extra: litellm
Requires-Dist: litellm<2.0,>=1.63.14; extra == "litellm"
Requires-Dist: python-dotenv==1.1.1; extra == "litellm"
Provides-Extra: vllm
Requires-Dist: vllm; extra == "vllm"
Provides-Extra: voting
Requires-Dist: pandas; extra == "voting"
Provides-Extra: retriever
Requires-Dist: sentence-transformers; extra == "retriever"
Requires-Dist: pyarrow; extra == "retriever"
Requires-Dist: elasticsearch<9.0.0,>=8.0.0; extra == "retriever"
Provides-Extra: dev
Requires-Dist: isort==7.0.0; extra == "dev"
Requires-Dist: pre-commit<5.0,>=3.0.4; extra == "dev"
Requires-Dist: pylint<5.0,>=2.16.2; extra == "dev"
Requires-Dist: pylint-pydantic; extra == "dev"
Requires-Dist: pytest; extra == "dev"
Requires-Dist: pytest-asyncio; extra == "dev"
Requires-Dist: pytest-cov; extra == "dev"
Requires-Dist: pytest-html; extra == "dev"
Requires-Dist: pytest-recording~=0.13.2; extra == "dev"
Requires-Dist: pytest-retry~=1.7; extra == "dev"
Requires-Dist: ruff==0.14.1; extra == "dev"
Requires-Dist: tox; extra == "dev"
Requires-Dist: anywidget; extra == "dev"
Requires-Dist: ipywidgets; extra == "dev"
Requires-Dist: vcrpy==6.0.2; extra == "dev"
Requires-Dist: granite-io[transformers]; extra == "dev"
Requires-Dist: granite-io[nltk]; extra == "dev"
Requires-Dist: granite-io[openai]; extra == "dev"
Requires-Dist: granite-io[litellm]; extra == "dev"
Requires-Dist: granite-io[voting]; extra == "dev"
Requires-Dist: granite-io[vllm]; extra == "dev"
Requires-Dist: granite-io[retriever]; extra == "dev"
Provides-Extra: notebook
Requires-Dist: notebook; extra == "notebook"
Requires-Dist: aiohttp; extra == "notebook"
Requires-Dist: granite-io[openai]; extra == "notebook"
Requires-Dist: granite-io[voting]; extra == "notebook"
Provides-Extra: all
Requires-Dist: granite-io[dev]; extra == "all"
Requires-Dist: granite-io[notebook]; extra == "all"
Dynamic: license-file
